ed25519_zebra.libs/libgcc_s-0366c7ba.so.1
ed25519_zebra/__init__.py
ed25519_zebra/ed25519_zebra.cpython-310-arm-linux-gnueabihf.so
py_ed25519_zebra_bindings-1.3.0.dist-info/METADATA
py_ed25519_zebra_bindings-1.3.0.dist-info/WHEEL
py_ed25519_zebra_bindings-1.3.0.dist-info/licenses/LICENSE
py_ed25519_zebra_bindings-1.3.0.dist-info/RECORD
