Metadata-Version: 2.4
Name: py-ed25519-zebra-bindings
Version: 1.3.0
Classifier: License :: OSI Approved :: Apache Software License
Classifier: Intended Audience :: Developers
Classifier: Programming Language :: Python :: 3.9
Classifier: Programming Language :: Python :: 3.10
Classifier: Programming Language :: Python :: 3.11
Classifier: Programming Language :: Python :: 3.12
Classifier: Programming Language :: Python :: 3.13
License-File: LICENSE
Summary: Python bindings for the ed25519-zebra RUST crate
Home-Page: https://github.com/polkascan/py-ed25519-zebra-bindings
Author-email: JAMdot Technologies <devops@jamdot.tech>
Maintainer-email: JAMdot Technologies <devops@jamdot.tech>
Requires-Python: >=3.9
Project-URL: repository, https://github.com/polkascan/py-ed25519-zebra-bindings
Project-URL: homepage, https://github.com/polkascan/py-ed25519-zebra-bindings
